mediachecker/__init__.py
mediachecker/cli.py
mediachecker-2022.9.19.dist-info/METADATA
mediachecker-2022.9.19.dist-info/WHEEL
mediachecker-2022.9.19.dist-info/entry_points.txt
mediachecker-2022.9.19.dist-info/licenses/LICENSE
mediachecker-2022.9.19.dist-info/RECORD
