Metadata-Version: 2.1
Name: mediachecker
Version: 2022.9.19
Summary: Check A/V files for corruption using ffmpeg.
Project-URL: Homepage, https://github.com/atpage/mediachecker
Project-URL: Bug Tracker, https://github.com/atpage/mediachecker/issues
Author-email: Alex Page <a.t.page@gmail.com>
License: MIT License
License-File: LICENSE
Classifier: License :: OSI Approved :: MIT License
Classifier: Operating System :: OS Independent
Classifier: Programming Language :: Python :: 3
Requires-Python: >=3.6
